README.md
setup.cfg
setup.py
primitive_interfaces/__init__.py
primitive_interfaces/base.py
primitive_interfaces/clustering.py
primitive_interfaces/distance.py
primitive_interfaces/featurization.py
primitive_interfaces/generator.py
primitive_interfaces/supervised_learning.py
primitive_interfaces/transformer.py
primitive_interfaces/unsupervised_learning.py
primitive_interfaces.egg-info/PKG-INFO
primitive_interfaces.egg-info/SOURCES.txt
primitive_interfaces.egg-info/dependency_links.txt
primitive_interfaces.egg-info/requires.txt
primitive_interfaces.egg-info/top_level.txt