Metadata-Version: 1.0
Name: primitive-interfaces
Version: 2018.1.26
Summary: Python interfaces for TA1 primitives
Home-page: https://gitlab.com/datadrivendiscovery/primitive-interfaces
Author: DARPA D3M Program
Author-email: UNKNOWN
License: UNKNOWN
Platform: UNKNOWN
